[
{"li": [{"id": 0, "img": "http://images.s.cn/images/goods/20160419/6a03e88588e0952c_210.jpg",
				"p1": "99.00&nbsp;", "s": "￥339.0", 
				"p2": "安踏", "span": "已经售出14件", "i": "尺码：36、37"},
		{"id": 1, "img": "http://images.s.cn/images/goods/20160606/fe6a2ee2d422d910_210.jpg",
				"p1": "99.00&nbsp;", "s": "￥339.0", 
				"p2": "安踏", "span": "已经售出14件", "i": "尺码：36、37"},
		{"id": 2, "img": "http://images.s.cn/images/goods/20160519/43b8f6710b3dcddb_210.jpg",
				"p1": "99.00&nbsp;", "s": "￥339.0", 
				"p2": "安踏", "span": "已经售出14件", "i": "尺码：36、37"},
		{"id": 3, "img": "http://images.s.cn/images/goods/20160719/69223f37f025e796_210.jpg",
				"p1": "99.00&nbsp;", "s": "￥339.0", 
				"p2": "安踏", "span": "已经售出14件", "i": "尺码：36、37"},
		{"id": 4, "img": "http://images.s.cn/images/goods/20160803/b5188451bf2f7068_210.jpg",
			"p1": "99.00&nbsp;", "s": "￥339.0", 
				"p2": "安踏", "span": "已经售出14件", "i": "尺码：36、37"},
		{"id": 5, "img": "http://images.s.cn/images/goods/20160419/6a03e88588e0952c_210.jpg",
				"p1": "99.00&nbsp;", "s": "￥339.0", 
				"p2": "安踏", "span": "已经售出14件", "i": "尺码：36、37"},
		{"id": 6, "img": "http://images.s.cn/images/goods/20160606/fe6a2ee2d422d910_210.jpg",
				"p1": "99.00&nbsp;", "s": "￥339.0", 
				"p2": "安踏", "span": "已经售出14件", "i": "尺码：36、37"},
		{"id": 7, "img": "http://images.s.cn/images/goods/20160519/43b8f6710b3dcddb_210.jpg",
				"p1": "99.00&nbsp;", "s": "￥339.0", 
				"p2": "安踏", "span": "已经售出14件", "i": "尺码：36、37"},
		{"id": 8, "img": "http://images.s.cn/images/goods/20160719/69223f37f025e796_210.jpg",
				"p1": "99.00&nbsp;", "s": "￥339.0", 
				"p2": "安踏", "span": "已经售出14件", "i": "尺码：36、37"},
		{"id": 9, "img": "http://images.s.cn/images/goods/20160803/b5188451bf2f7068_210.jpg",
			"p1": "99.00&nbsp;", "s": "￥339.0", 
				"p2": "安踏", "span": "已经售出14件", "i": "尺码：36、37"},
		{"id": 10, "img": "http://images.s.cn/images/goods/20160419/6a03e88588e0952c_210.jpg",
				"p1": "99.00&nbsp;", "s": "￥339.0", 
				"p2": "安踏", "span": "已经售出14件", "i": "尺码：36、37"},
		{"id": 11, "img": "http://images.s.cn/images/goods/20160606/fe6a2ee2d422d910_210.jpg",
				"p1": "99.00&nbsp;", "s": "￥339.0", 
				"p2": "安踏", "span": "已经售出14件", "i": "尺码：36、37"},
		{"id": 12, "img": "http://images.s.cn/images/goods/20160519/43b8f6710b3dcddb_210.jpg",
				"p1": "99.00&nbsp;", "s": "￥339.0", 
				"p2": "安踏", "span": "已经售出14件", "i": "尺码：36、37"},
		{"id": 13, "img": "http://images.s.cn/images/goods/20160719/69223f37f025e796_210.jpg",
				"p1": "99.00&nbsp;", "s": "￥339.0", 
				"p2": "安踏", "span": "已经售出14件", "i": "尺码：36、37"},
		{"id": 14, "img": "http://images.s.cn/images/goods/20160803/b5188451bf2f7068_210.jpg",
			"p1": "99.00&nbsp;", "s": "￥339.0", 
				"p2": "安踏", "span": "已经售出14件", "i": "尺码：36、37"}]}
]

